README.txt
setup.cfg
setup.py
ogr_utils/__init__.py
ogr_utils/copy_helper.py
ogr_utils/extractor.py
ogr_utils/geometry.py
ogr_utils/ogr_utils.py
ogr_utils/research.py
ogr_utils.egg-info/PKG-INFO
ogr_utils.egg-info/SOURCES.txt
ogr_utils.egg-info/dependency_links.txt
ogr_utils.egg-info/entry_points.txt
ogr_utils.egg-info/not-zip-safe
ogr_utils.egg-info/requires.txt
ogr_utils.egg-info/top_level.txt
ogr_utils/tests/__init__.py
ogr_utils/tests/test_copy_helper.py
ogr_utils/tests/test_geometry.py
ogr_utils/tests/test_ogr_utils.py