Metadata-Version: 1.1
Name: ogr-utils
Version: 1.2
Summary: conveniance utilities for ogr
Home-page: http://www.and.com/
Author: Lars Claussen, Thijs Creemers
Author-email: lars.claussen@and.com
License: UNKNOWN
Keywords: org utility
Platform: UNKNOWN
Classifier: Programming Language :: Python :: 2.7
Classifier: Topic :: Scientific/Engineering :: GIS
